path_explain/__init__.py
path_explain/utils.py
path_explain/explainers/__init__.py
path_explain/explainers/embedding_explainer_tf.py
path_explain/explainers/explainer.py
path_explain/explainers/path_explainer_tf.py
path_explain/explainers/path_explainer_torch.py
path_explain/plot/__init__.py
path_explain/plot/colors.py
path_explain/plot/scatter.py
path_explain/plot/summary.py
path_explain/plot/text.py
path_explain-0.0.7.dist-info/LICENSE
path_explain-0.0.7.dist-info/METADATA
path_explain-0.0.7.dist-info/WHEEL
path_explain-0.0.7.dist-info/top_level.txt
path_explain-0.0.7.dist-info/RECORD
