Metadata-Version: 2.1
Name: path-explain
Version: 0.0.7
Summary: A package for explaining attributions and interactions in deep neural networks
Home-page: https://github.com/suinleelab/path_explain
Author: Joseph Janizek, Pascal Sturmfels
Author-email: jjanizek@uw.edu
License: UNKNOWN
Platform: UNKNOWN
Classifier: Programming Language :: Python :: 3
Classifier: License :: OSI Approved :: MIT License
Classifier: Operating System :: OS Independent
Classifier: Intended Audience :: Science/Research
Classifier: Topic :: Scientific/Engineering
Requires-Python: >=3.6
License-File: LICENSE
